LICENSE
MANIFEST.in
README.rst
setup.py
eea.flis.metadata.egg-info/PKG-INFO
eea.flis.metadata.egg-info/SOURCES.txt
eea.flis.metadata.egg-info/dependency_links.txt
eea.flis.metadata.egg-info/requires.txt
eea.flis.metadata.egg-info/top_level.txt
flis_metadata/__init__.py
flis_metadata/client/__init__.py
flis_metadata/client/management/__init__.py
flis_metadata/client/management/commands/__init__.py
flis_metadata/client/management/commands/sync_remote_models.py
flis_metadata/common/__init__.py
flis_metadata/common/models.py
flis_metadata/common/views.py
flis_metadata/common/fixtures/initial_countries.json
flis_metadata/common/fixtures/initial_geo_scope.json
flis_metadata/common/fixtures/initial_themes.json
flis_metadata/common/management/__init__.py
flis_metadata/common/management/commands/__init__.py
flis_metadata/common/management/commands/load_metadata_fixtures.py
flis_metadata/common/migrations/0001_initial.py
flis_metadata/common/migrations/0002_auto_20150615_1322.py
flis_metadata/common/migrations/__init__.py