Metadata-Version: 1.1
Name: eea.flis.metadata
Version: 0.6.2
Summary: EEA Metadata models replication support
Home-page: https://github.com/eea/flis.metadata
Author: Mihai Bivol
Author-email: mm.bivol@gmail.com
License: BSD License
Platform: UNKNOWN
Classifier: Environment :: Web Environment
Classifier: Framework :: Django
Classifier: Intended Audience :: Developers
Classifier: License :: OSI Approved :: BSD License
Classifier: Operating System :: OS Independent
Classifier: Programming Language :: Python
Classifier: Programming Language :: Python :: 2.6
Classifier: Programming Language :: Python :: 2.7
Classifier: Topic :: Internet :: WWW/HTTP
Classifier: Topic :: Internet :: WWW/HTTP :: Dynamic Content
